LICENSE
README.md
setup.py
invoiceonator/__init__.py
invoiceonator/__main__.py
invoiceonator/components.py
invoiceonator/invoice.py
invoiceonator/io.py
invoiceonator/template.py
invoiceonator.egg-info/PKG-INFO
invoiceonator.egg-info/SOURCES.txt
invoiceonator.egg-info/dependency_links.txt
invoiceonator.egg-info/entry_points.txt
invoiceonator.egg-info/requires.txt
invoiceonator.egg-info/top_level.txt